PdfDarkMode/__init__.py
PdfDarkMode/darkmode.py
PdfDarkMode-1.0.5.dist-info/LICENSE
PdfDarkMode-1.0.5.dist-info/METADATA
PdfDarkMode-1.0.5.dist-info/WHEEL
PdfDarkMode-1.0.5.dist-info/top_level.txt
PdfDarkMode-1.0.5.dist-info/RECORD
