Metadata-Version: 2.1
Name: PdfDarkMode
Version: 1.0.5
Summary: Converts PDFs to have a grey background to be easier on the eyes
Home-page: https://github.com/JustinTheWhale/PDF-Dark-Mode
Author: JustinTheWhale
Author-email: justinraymen@gmail.com
License-File: LICENSE
Requires-Dist: opencv-python
Requires-Dist: numpy
Requires-Dist: fpdf
Requires-Dist: numba
Requires-Dist: pdf2image
Requires-Dist: Pillow
Requires-Dist: PyPDF2
